setup.py
psychic/__init__.py
psychic/psychic.py
psychic/testfile.c.jinja
psychic.egg-info/PKG-INFO
psychic.egg-info/SOURCES.txt
psychic.egg-info/dependency_links.txt
psychic.egg-info/entry_points.txt
psychic.egg-info/requires.txt
psychic.egg-info/top_level.txt
psychic/csource/__init__.py
psychic/csource/psychic.c
psychic/csource/psychic.h
psychic/csource/psychic_share.h