Metadata-Version: 1.0
Name: psychic
Version: 1.1.0
Summary: Unit testing library for C - powered by python
Home-page: https://github.com/dudadornelles/psychic
Author: Duda Dornelles
Author-email: dudassdornelles@gmail.com
License: Apache2
Keywords: c unit test
Platform: UNKNOWN
